nonebot_plugin_setu_customization/__init__.py
nonebot_plugin_setu_customization/config.py
nonebot_plugin_setu_customization/data_handle.py
nonebot_plugin_setu_customization-2.3.10.dist-info/METADATA
nonebot_plugin_setu_customization-2.3.10.dist-info/WHEEL
nonebot_plugin_setu_customization-2.3.10.dist-info/RECORD
