Metadata-Version: 2.1
Name: nonebot_plugin_setu_customization
Version: 2.3.10
Summary: Nonebot2 可动态管理API的setu(色图)插件
Home-page: https://github.com/nikissXI/nonebot_plugins/tree/main/nonebot_plugin_setu_customization
License: MIT
Author: nikissXI
Author-email: 1299577815@qq.com
Requires-Python: >=3.8
Classifier: License :: OSI Approved :: MIT License
Classifier: Programming Language :: Python :: 3
Classifier: Programming Language :: Python :: 3.8
Classifier: Programming Language :: Python :: 3.9
Classifier: Programming Language :: Python :: 3.10
Classifier: Programming Language :: Python :: 3.11
Classifier: Programming Language :: Python :: 3.12
Requires-Dist: aiohttp (>=3.10.0)
Requires-Dist: nonebot-adapter-onebot (>=2.0.0)
Requires-Dist: nonebot2 (>=2.0.0rc1)
Project-URL: Documentation, https://github.com/nikissXI/nonebot_plugins/tree/main/nonebot_plugin_setu_customization#README.md
Project-URL: Repository, https://github.com/nikissXI/nonebot_plugins/tree/main/nonebot_plugin_setu_customization
